odoo10_addon_web_translate_dialog-10.0.1.0.1-py2.7-nspkg.pth
odoo/addons/web_translate_dialog/README.rst
odoo/addons/web_translate_dialog/__init__.py
odoo/addons/web_translate_dialog/__manifest__.py
odoo/addons/web_translate_dialog/i18n/ar.po
odoo/addons/web_translate_dialog/i18n/de.po
odoo/addons/web_translate_dialog/i18n/es.po
odoo/addons/web_translate_dialog/i18n/fi.po
odoo/addons/web_translate_dialog/i18n/fr.po
odoo/addons/web_translate_dialog/i18n/hr.po
odoo/addons/web_translate_dialog/i18n/it.po
odoo/addons/web_translate_dialog/i18n/nl.po
odoo/addons/web_translate_dialog/i18n/nl_NL.po
odoo/addons/web_translate_dialog/i18n/pt_BR.po
odoo/addons/web_translate_dialog/i18n/sl.po
odoo/addons/web_translate_dialog/i18n/tr.po
odoo/addons/web_translate_dialog/i18n/web_translate_dialog.pot
odoo/addons/web_translate_dialog/static/description/icon.png
odoo/addons/web_translate_dialog/static/src/css/base.css
odoo/addons/web_translate_dialog/static/src/js/web_translate_dialog.js
odoo/addons/web_translate_dialog/static/src/xml/base.xml
odoo/addons/web_translate_dialog/view/web_translate.xml
odoo10_addon_web_translate_dialog-10.0.1.0.1.dist-info/DESCRIPTION.rst
odoo10_addon_web_translate_dialog-10.0.1.0.1.dist-info/METADATA
odoo10_addon_web_translate_dialog-10.0.1.0.1.dist-info/RECORD
odoo10_addon_web_translate_dialog-10.0.1.0.1.dist-info/WHEEL
odoo10_addon_web_translate_dialog-10.0.1.0.1.dist-info/metadata.json
odoo10_addon_web_translate_dialog-10.0.1.0.1.dist-info/namespace_packages.txt
odoo10_addon_web_translate_dialog-10.0.1.0.1.dist-info/top_level.txt
