Metadata-Version: 2.0
Name: odoo10-addon-web-translate-dialog
Version: 10.0.1.0.1
Summary: Easy-to-use pop-up to translate fields in several languages
Home-page: https://odoo-community.org/
Author: Camptocamp, Tecnativa, Odoo Community Association (OCA)
Author-email: support@odoo-community.org
License: AGPL-3
Platform: UNKNOWN
Classifier: Programming Language :: Python
Classifier: Framework :: Odoo
Classifier: License :: OSI Approved :: GNU Affero General Public License v3
Requires-Python: ~=2.7
Requires-Dist: odoo (<10.1dev,>=10.0)
